MANIFEST.in
requirements.txt
setup.py
pyres/__init__.py
pyres/compat.py
pyres/exceptions.py
pyres/extensions.py
pyres/horde.py
pyres/job.py
pyres/json_parser.py
pyres/scheduler.py
pyres/scripts.py
pyres/worker.py
pyres.egg-info/PKG-INFO
pyres.egg-info/SOURCES.txt
pyres.egg-info/dependency_links.txt
pyres.egg-info/entry_points.txt
pyres.egg-info/requires.txt
pyres.egg-info/top_level.txt
pyres/failure/__init__.py
pyres/failure/base.py
pyres/failure/mail.py
pyres/failure/multiple.py
pyres/failure/redis.py