Metadata-Version: 1.1
Name: pyres
Version: 1.5
Summary: Python resque clone
Home-page: http://github.com/binarydud/pyres
Author: Matt George
Author-email: mgeorge@gmail.com
License: MIT
Download-URL: http://pypi.python.org/packages/source/p/pyres/pyres-1.5.tar.gz
Platform: UNKNOWN
Classifier: Development Status :: 4 - Beta
Classifier: Environment :: Console
Classifier: Intended Audience :: Developers
Classifier: License :: OSI Approved :: MIT License
Classifier: Operating System :: OS Independent
Classifier: Programming Language :: Python :: 2.6
Classifier: Programming Language :: Python :: 2.7
Classifier: Programming Language :: Python :: 3.3
Classifier: Programming Language :: Python
